AUTHORS.rst
HISTORY.rst
LICENSE
MANIFEST.in
Makefile
README.md
README.rst
setup.cfg
setup.py
usig_normalizador_amba/Calle.py
usig_normalizador_amba/Callejero.py
usig_normalizador_amba/Direccion.py
usig_normalizador_amba/Errors.py
usig_normalizador_amba/NormalizadorDirecciones.py
usig_normalizador_amba/NormalizadorDireccionesAMBA.py
usig_normalizador_amba/Partido.py
usig_normalizador_amba/Punto.py
usig_normalizador_amba/StringDireccion.py
usig_normalizador_amba/__init__.py
usig_normalizador_amba/commons.py
usig_normalizador_amba/settings.py
usig_normalizador_amba.egg-info/PKG-INFO
usig_normalizador_amba.egg-info/SOURCES.txt
usig_normalizador_amba.egg-info/dependency_links.txt
usig_normalizador_amba.egg-info/top_level.txt