Metadata-Version: 1.1
Name: usig-normalizador-amba
Version: 1.3.0
Summary: Normalizador de Direcciones AMBA
Home-page: https://github.com/usig/normalizador-amba
Author: DGCINF - USIG - GCBA
Author-email: USIG - Desarrollo <mapa@buenosaires.gob.ar>
License: MIT License
Keywords: usig gcba gis normalizador direcciones amba
Platform: Unix/Linux
Classifier: Development Status :: 5 - Production/Stable
Classifier: Intended Audience :: Developers
Classifier: License :: OSI Approved :: MIT License
Classifier: Natural Language :: Spanish
Classifier: Operating System :: Unix
Classifier: Programming Language :: Python :: 3.6
Classifier: Topic :: Scientific/Engineering :: GIS
Classifier: Topic :: Software Development :: Libraries :: Python Modules
